{"container":"_container_1reci_3","relative":"_relative_1reci_14","fixed":"_fixed_1reci_18","absolute":"_absolute_1reci_25","sticky":"_sticky_1reci_32","scroll-button":"_scroll-button_1reci_38","scroll-button--hidden":"_scroll-button--hidden_1reci_1","scroll-box-clipper":"_scroll-box-clipper_1reci_61","test-horizontal-scrollbar-height":"_test-horizontal-scrollbar-height_1reci_65","scroll-box":"_scroll-box_1reci_61","scroll-area":"_scroll-area_1reci_88","tab-container":"_tab-container_1reci_96","contained":"_contained_1reci_100","tab":"_tab_1reci_96","cluster-centered":"_cluster-centered_1reci_114","d2ui-tabs__scroll-area":"_d2ui-tabs__scroll-area_1reci_1","d2ui-tabs__tab-container":"_d2ui-tabs__tab-container_1reci_1","active":"_active_1reci_152","disabled":"_disabled_1reci_156","stacked":"_stacked_1reci_161","material-icons":"_material-icons_1reci_165","tab-indicator":"_tab-indicator_1reci_177","visible":"_visible_1reci_195","animated":"_animated_1reci_199"}