{"d2ui-headerbar":"_d2ui-headerbar_yvkls_3","logo":"_logo_yvkls_16","title":"_title_yvkls_23","current-selection":"_current-selection_yvkls_34","notification":"_notification_yvkls_45","email":"_email_yvkls_50","count":"_count_yvkls_54","apps-container":"_apps-container_yvkls_75","profile":"_profile_yvkls_85","icon":"_icon_yvkls_91","initials":"_initials_yvkls_103","contents":"_contents_yvkls_118","header":"_header_yvkls_132","details":"_details_yvkls_143","name":"_name_yvkls_152","edit_profile":"_edit_profile_yvkls_160","divider":"_divider_yvkls_168","menu":"_menu_yvkls_174","item":"_item_yvkls_178","label":"_label_yvkls_191","d2ui-headerbar--blue":"_d2ui-headerbar--blue_yvkls_1","d2ui-headerbar--white":"_d2ui-headerbar--white_yvkls_1","d2ui-headerbar--transparent":"_d2ui-headerbar--transparent_yvkls_1"}